LICENSE
README.md
setup.py
luminara/__init__.py
luminara.egg-info/PKG-INFO
luminara.egg-info/SOURCES.txt
luminara.egg-info/dependency_links.txt
luminara.egg-info/requires.txt
luminara.egg-info/top_level.txt