Metadata-Version: 2.1
Name: luminara
Version: 0.0.1
Summary: ex.
Home-page: https://github.com/ishanoshada/luminara
Author: Ishan Oshada
Author-email: ishan.kodithuwakku.official@email.com
Classifier: Programming Language :: Python :: 3
Classifier: License :: OSI Approved :: MIT License
Classifier: Operating System :: OS Independent
License-File: LICENSE
Requires-Dist: requests
